{"state":{"token":"eyJhbGciOiJIUzI1NiIsInR5cCI6IkpXVCJ9.eyJ1c2VySWQiOjM0MjA2NywidGltZXN0YW1wIjoxNzE2OTcyODAwMTk3LCJ0eXBlIjoxLCJpYXQiOjE3MTY5NzI4MDAsImV4cCI6MTcxNzU3NzYwMH0.5rm-MOZk85GjGUKk1SZoUoU1PbMqNh6ysF7c-3B1_6o","userInfo":{"id":342067,"email":null,"mobile":null,"username":null,"address":null,"avatar":"https://quackquack-prj.s3.ap-southeast-1.amazonaws.com/avatar/default.jpg","fullName":null,"status":2,"lastActive":null,"type":1,"referralCode":"6hn8Xrp7DK","telegramId":697371752,"telegramData":{"id":697371752,"username":"mhqb365","lastName":"Mai","firstName":"Hoàng Quốc Bảo","languageCode":"vi","allowsWriteToPm":true},"createdTime":"2024-05-22T15:33:07.357Z","updatedTime":"2024-05-22T16:00:48.904Z","googleId":null,"facebookId":null,"fileId":null,"tier":1,"twitterId":"1170728730718687238","twitterData":{"id":"1170728730718687238","name":"Mai Hoàng Quốc Bảo","username":"mhqb365"},"twitterAccessToken":"Q1JScmtGNTJOelRHZ1NnbFdpWjJYbF9ERnVUNG92ZmVnLXNZVzNvTGNXZm5MOjE3MTYzOTM2NDgxODc6MToxOmF0OjE"}},"version":0}